Metadata-Version: 2.1
Name: commit-msg-hook
Version: 0.3.4
Summary: Checks if commit message matches the chaos-hub commit rules
Home-page: https://github.com/dimaka-wix/commit-msg-hook.git
Author: Dima Karpukhin
Author-email: dimaka@wix.com
License: MIT
Platform: UNKNOWN
Classifier: Programming Language :: Python :: 3
Classifier: License :: OSI Approved :: MIT License
Classifier: Operating System :: OS Independent
Requires-Python: >=3.6
License-File: LICENSE
Requires-Dist: nltk
